neuralezee/__init__.py
neuralezee/knn.py
neuralezee/knn_beta.py
neuralezee-0.0.2.dist-info/METADATA
neuralezee-0.0.2.dist-info/WHEEL
neuralezee-0.0.2.dist-info/licenses/LICENSE
neuralezee-0.0.2.dist-info/RECORD
