Metadata-Version: 2.1
Name: neuralezee
Version: 0.0.2
Summary: Machine Learning
Project-URL: Homepage, https://github.com/UMITxGOD/MachineLearning
Project-URL: Bug Tracker, https://github.com/UMITxGOD/MachineLearning/issues
Author-email: umit kumar sahoo <umitkumarsahoo111@gmail.com>
License: Copyright (c) 2022 UMIT
License-File: LICENSE
Classifier: License :: OSI Approved :: MIT License
Classifier: Operating System :: OS Independent
Classifier: Programming Language :: Python :: 3
Requires-Python: >=3.7
